.coveragerc
CHANGES.md
LICENSE
MANIFEST.in
README.rst
paleomix_environment.yaml
setup.cfg
setup.py
tox.ini
docs/Makefile
docs/acknowledgements.rst
docs/conf.py
docs/examples.rst
docs/index.rst
docs/installation.rst
docs/introduction.rst
docs/other_tools.rst
docs/references.rst
docs/related.rst
docs/release.rst
docs/yaml.rst
docs/_static/zonkey/incl_ts_0_tree_rooted.png
docs/_static/zonkey/incl_ts_0_tree_unrooted.png
docs/_static/zonkey/mito_phylo.png
docs/bam_pipeline/configuration.rst
docs/bam_pipeline/filestructure.rst
docs/bam_pipeline/index.rst
docs/bam_pipeline/makefile.rst
docs/bam_pipeline/makefile.yaml
docs/bam_pipeline/overview.rst
docs/bam_pipeline/requirements.rst
docs/bam_pipeline/usage.rst
docs/phylo_pipeline/configuration.rst
docs/phylo_pipeline/filestructure.rst
docs/phylo_pipeline/index.rst
docs/phylo_pipeline/makefile.rst
docs/phylo_pipeline/overview.rst
docs/phylo_pipeline/requirements.rst
docs/phylo_pipeline/usage.rst
docs/troubleshooting/bam_pipeline.rst
docs/troubleshooting/common.rst
docs/troubleshooting/index.rst
docs/troubleshooting/install.rst
docs/troubleshooting/phylo_pipeline.rst
docs/troubleshooting/zonkey_pipeline.rst
docs/zonkey_pipeline/configuration.rst
docs/zonkey_pipeline/filestructure.rst
docs/zonkey_pipeline/index.rst
docs/zonkey_pipeline/overview.rst
docs/zonkey_pipeline/panel.rst
docs/zonkey_pipeline/requirements.rst
docs/zonkey_pipeline/usage.rst
misc/setup_bam_pipeline_example.makefile.yaml
misc/setup_bam_pipeline_example.sh
misc/setup_phylo_pipeline_example.sh
misc/skeleton.py
misc/synthesize_reads.py
paleomix/__init__.py
paleomix/main.py
paleomix/node.py
paleomix/nodegraph.py
paleomix/pipeline.py
paleomix/yaml.py
paleomix.egg-info/PKG-INFO
paleomix.egg-info/SOURCES.txt
paleomix.egg-info/dependency_links.txt
paleomix.egg-info/entry_points.txt
paleomix.egg-info/not-zip-safe
paleomix.egg-info/requires.txt
paleomix.egg-info/top_level.txt
paleomix/atomiccmd/__init__.py
paleomix/atomiccmd/builder.py
paleomix/atomiccmd/command.py
paleomix/atomiccmd/pprint.py
paleomix/atomiccmd/sets.py
paleomix/common/__init__.py
paleomix/common/argparse.py
paleomix/common/bamfiles.py
paleomix/common/bedtools.py
paleomix/common/fileutils.py
paleomix/common/logging.py
