Metadata-Version: 2.1
Name: paleomix
Version: 1.3.10
Summary: Bioinformatics pipelines for HTS data
Home-page: https://github.com/MikkelSchubert/paleomix
Author: Mikkel Schubert
Author-email: MikkelSch@gmail.com
License: MIT
Keywords: pipeline bioinformatics hts phylogeny bam
Classifier: Development Status :: 5 - Production/Stable
Classifier: Intended Audience :: Science/Research
Classifier: Topic :: Scientific/Engineering :: Bio-Informatics
Classifier: License :: OSI Approved :: MIT License
Classifier: Programming Language :: Python :: 3 :: Only
Classifier: Programming Language :: Python :: 3.5
Classifier: Programming Language :: Python :: 3.6
Classifier: Programming Language :: Python :: 3.7
Classifier: Programming Language :: Python :: 3.8
Classifier: Programming Language :: Python :: 3.9
Classifier: Programming Language :: Python :: 3.10
Classifier: Programming Language :: Python :: 3.11
License-File: LICENSE
